Metadata-Version: 2.1
Name: ouo-io-api
Version: 1.0
Summary: an api for the ouo.io link shortener service
Home-page: https://github.com/h-enes-simsek/ouo-io-api
Author: Hasan Enes Şimşek
Author-email: enes1406@gmail.com
License: MIT
Keywords: ouo,ouo-io,link-shortener
Platform: UNKNOWN
Classifier: Programming Language :: Python :: 3
Classifier: License :: OSI Approved :: MIT License
Classifier: Operating System :: OS Independent
Classifier: Development Status :: 5 - Production/Stable
Requires-Python: >=3
License-File: LICENSE.txt
